Metadata-Version: 1.0
Name: Jayanti-distributions
Version: 2.0
Summary: Gaussian distributions and Binomial Distributions
Home-page: UNKNOWN
Author: Jayanti Vishnoi
Author-email: hasbrovish95@gmail.com
License: UNKNOWN
Platform: UNKNOWN
